sysdi/__init__.py
sysdi/cli.py
sysdi/core.py
sysdi/ping.py
sysdi/utils.py
sysdi/version.py
sysdi/contrib/__init__.py
sysdi/contrib/cronitor.py
sysdi-0.20260116.2.dist-info/METADATA
sysdi-0.20260116.2.dist-info/WHEEL
sysdi-0.20260116.2.dist-info/entry_points.txt
sysdi-0.20260116.2.dist-info/RECORD
