Metadata-Version: 2.4
Name: sysdi
Version: 0.20260116.2
Author-email: Randy Syring <randy.syring@level12.io>
Requires-Python: ~=3.12.0
Requires-Dist: blazeutils>=0.7.0
Requires-Dist: furl>=2.1.4
